lofi_gate/__init__.py
lofi_gate/cli.py
lofi_gate/logger.py
lofi_gate/logic.py
lofi_gate/templates/judge.py
lofi_gate-0.1.4.dist-info/licenses/LICENSE
lofi_gate-0.1.4.dist-info/METADATA
lofi_gate-0.1.4.dist-info/WHEEL
lofi_gate-0.1.4.dist-info/entry_points.txt
lofi_gate-0.1.4.dist-info/top_level.txt
lofi_gate-0.1.4.dist-info/RECORD
