Metadata-Version: 2.4
Name: lofi-gate
Version: 0.1.4
Summary: Signal-first verification for AI coding agents.
Author-email: LoFi Monk <lofi@example.com>
License: MIT License
Classifier: Programming Language :: Python :: 3
Classifier: License :: OSI Approved :: MIT License
Classifier: Operating System :: OS Independent
Requires-Python: >=3.8
License-File: LICENSE
Requires-Dist: click>=8.0.0
Requires-Dist: rich>=10.0.0
Requires-Dist: tiktoken>=0.3.0
Requires-Dist: toml>=0.10.0
Provides-Extra: dev
Requires-Dist: pytest; extra == "dev"
Dynamic: license-file
